{
  "timestamp": "2025-07-23T22:40:07.16495838+02:00",
  "host": "127.0.0.1",
  "base_port": 9000,
  "protocols": {
    "obfs4": {
      "protocol": "obfs4",
      "port": 9000,
      "credentials": {
        "certificate": "OnsfSmbXtt9gX18tWMyStK5GLOtu7JjjXvD4LwH6Dx7oCa09RAMOBX6mny5Rt24R4yG8MA",
        "iat_mode": "0"
      }
    },
    "quic": {
      "protocol": "quic",
      "port": 9005,
      "credentials": {
        "enable_datagrams": "true",
        "max_idle_timeout": "30s",
        "max_incoming_streams": "100",
        "versions": "1"
      }
    },
    "shadowsocks": {
      "protocol": "shadowsocks",
      "port": 9004,
      "credentials": {
        "method": "chacha20-ietf-poly1305",
        "password": "gH5LLh1WAD^yq!IP"
      }
    },
    "vless": {
      "protocol": "vless",
      "port": 9001,
      "credentials": {
        "encryption": "none",
        "flow": "xtls-rprx-vision",
        "network": "tcp",
        "security": "none",
        "uuid": "caba3b61-892d-4ec0-858c-6b1b8194d28f"
      }
    },
    "vmess": {
      "protocol": "vmess",
      "port": 9002,
      "credentials": {
        "encryption": "auto",
        "host": "localhost",
        "network": "ws",
        "path": "/ws",
        "uuid": "c354518c-bf2b-46ac-b5fc-562584f8ca19"
      }
    },
    "xtls": {
      "protocol": "xtls",
      "port": 9003,
      "credentials": {
        "alpn": "http/1.1",
        "flow": "xtls-rprx-vision",
        "network": "tcp",
        "security": "xtls",
        "server_name": "localhost",
        "uuid": "0c680767-1dc8-4893-9b40-5ff67c01a68c"
      }
    }
  }
}